{
    "24836a2c-e8fa-4af1-865e-a27f5adebe3f": {
        "type": "benign",
        "resp": "{\"approved\":\"true\",\"authorization\":891507959501329}"
    },
    "9b746655-bd08-4ded-aae7-a6f53f45782f": {
        "type": "benign",
        "resp": "{\"approved\":\"true\",\"authorization\":2464025315565645}"
    },
    "4684ed18-9cd7-40db-97a4-aecf7fc784cd": {
        "type": "benign",
        "resp": "{\"approved\":\"true\",\"authorization\":2806916304713221}"
    },
    "600cc70a-31ce-46e9-8b8b-850e6a82e2cb": {
        "type": "benign",
        "resp": "{\"approved\":\"true\",\"authorization\":5083840932767495}"
    },
    "19d2ec47-3206-4e67-9ab7-47a33bf5db33": {
        "type": "benign",
        "resp": "{\"approved\":\"true\",\"authorization\":6874113656610969}"
    },
    "eadcb780-7fe7-4c65-8540-28a1386e029d": {
        "type": "benign",
        "resp": "{\"approved\":\"true\",\"authorization\":6506978233929185}"
    },
    "0be12011-78c0-46fb-b3f1-e6be54e1beb6": {
        "type": "benign",
        "resp": "{\"approved\":\"true\",\"authorization\":5916710085051369}"
    },
    "7c246243-bfb2-4317-bbaf-a89770a7b292": {
        "type": "benign",
        "resp": "{\"approved\":\"true\",\"authorization\":1851535258029061}"
    },
    "505c210b-fa74-465b-90f5-8172ea4deb4c": {
        "type": "benign",
        "resp": "{\"approved\":\"true\",\"authorization\":4407050918501699}"
    },
    "3e484c97-35cf-472e-b924-a3ed60c8a173": {
        "type": "benign",
        "resp": "{\"approved\":\"false\",\"failureReason\":\"Credit card authorization failed\"}"
    },
    "aeeedf3e-95b7-48e8-a439-539d8af25bae": {
        "type": "benign",
        "resp": "{\"approved\":\"true\",\"authorization\":1486065340582891}"
    },
    "f2008a5e-dfcd-4456-a783-d7ea4ccef657": {
        "type": "benign",
        "resp": "{\"approved\":\"true\",\"authorization\":1564369489273823}"
    },
    "753c041b-e644-4f2d-8cf5-278258502ccb": {
        "type": "benign",
        "resp": "{\"approved\":\"true\",\"authorization\":1369265184676771}"
    },
    "3be39e21-e071-467c-8c08-ca4c68c3e379": {
        "type": "benign",
        "resp": "{\"approved\":\"true\",\"authorization\":7080075715971091}"
    },
    "7a44d9f6-41db-4ac3-ae0c-c9015ae24218": {
        "type": "benign",
        "resp": "{\"approved\":\"true\",\"authorization\":7507465965270351}"
    },
    "eb4d10f3-7713-4295-9e32-b0e721a987ae": {
        "type": "benign",
        "resp": "{\"approved\":\"true\",\"authorization\":1383846889513637}"
    },
    "2c03cc90-40f3-4ef9-8963-4fce1051851b": {
        "type": "benign",
        "resp": "{\"approved\":\"true\",\"authorization\":7390429644636129}"
    },
    "abdee7f2-63fa-48bb-bcd8-1d8db21f1f6f": {
        "type": "benign",
        "resp": "{\"approved\":\"true\",\"authorization\":3758073286553391}"
    },
    "5d96240b-491a-4bd7-a712-af3371218a0b": {
        "type": "benign",
        "resp": "{\"approved\":\"true\",\"authorization\":2582237898610277}"
    },
    "64b425c4-0e92-4062-823c-a41b539955a5": {
        "type": "benign",
        "resp": "{\"approved\":\"true\",\"authorization\":5227606468087681}"
    },
    "63c967d9-6cc3-4ed1-9623-8ee84039c5f6": {
        "type": "benign",
        "resp": "{\"approved\":\"true\",\"authorization\":3804349050275509}"
    },
    "577facaf-44b7-41c0-a75e-02c6a1815ea4": {
        "type": "benign",
        "resp": "{\"approved\":\"true\",\"authorization\":162327517700067}"
    },
    "fa5d1ce6-b1fc-4327-9080-b5979c3d84b7": {
        "type": "benign",
        "resp": "{\"approved\":\"true\",\"authorization\":5487273636877379}"
    },
    "19d1a04b-2ea5-401b-bfde-97a2359d5bbb": {
        "type": "benign",
        "resp": "{\"approved\":\"true\",\"authorization\":5806690212947285}"
    },
    "2879936c-49e5-4356-b15b-4530497bb3ea": {
        "type": "benign",
        "resp": "{\"approved\":\"true\",\"authorization\":3719558316976927}"
    },
    "2afb7c9c-3274-4878-a64f-19e6d86ed69b": {
        "type": "benign",
        "resp": "{\"approved\":\"true\",\"authorization\":8304935175212005}"
    },
    "bdb20597-697d-4d43-98e9-4ee49bfa435c": {
        "type": "attack",
        "resp": "{\"data\":\"done\"}"
    },
    "019a531c-1efe-4d19-9d76-d510c6146aa3": {
        "type": "benign",
        "resp": "{\"approved\":\"true\",\"authorization\":8653178401843769}"
    },
    "2e15d0ba-2ab9-484a-a8bd-04c56ecacfbe": {
        "type": "benign",
        "resp": "{\"approved\":\"true\",\"authorization\":4757207753875857}"
    },
    "9cfc9b33-43ab-4bd1-a5cd-f898d8a6fb04": {
        "type": "benign",
        "resp": "{\"approved\":\"true\",\"authorization\":2246916653365115}"
    },
    "e56c58df-c818-4049-a156-4771422c726e": {
        "type": "benign",
        "resp": "{\"approved\":\"true\",\"authorization\":2727842987363203}"
    },
    "86c8009a-0b51-49df-b63b-4767124b1eb2": {
        "type": "benign",
        "resp": "{\"approved\":\"true\",\"authorization\":4476642583863195}"
    },
    "ff1b56fe-734a-439b-93b0-187fc05aca27": {
        "type": "benign",
        "resp": "{\"approved\":\"true\",\"authorization\":4393054780193335}"
    },
    "5d84e01b-14b3-413d-acfa-367c261148c4": {
        "type": "benign",
        "resp": "{\"approved\":\"true\",\"authorization\":2884752978907403}"
    },
    "94c98608-d5f4-40e9-9977-b6ba911a497c": {
        "type": "benign",
        "resp": "{\"approved\":\"true\",\"authorization\":2303741757211205}"
    },
    "59d2d9a9-85a0-4e49-91ec-e54c0ebe2538": {
        "type": "benign",
        "resp": "{\"approved\":\"true\",\"authorization\":1046812633573993}"
    },
    "97bdb54a-65bb-4a89-bb8f-dde6517cda46": {
        "type": "benign",
        "resp": "{\"approved\":\"true\",\"authorization\":8372589998697095}"
    },
    "fea12c49-f416-4d24-b6bc-7fa83fad0539": {
        "type": "benign",
        "resp": "{\"approved\":\"true\",\"authorization\":1411776083187991}"
    },
    "d71804a6-0d7a-4214-832b-26a7d7de1222": {
        "type": "benign",
        "resp": "{\"approved\":\"true\",\"authorization\":7189152850604625}"
    },
    "be6a7919-c459-4696-a18e-41539a82a5e7": {
        "type": "benign",
        "resp": "{\"approved\":\"true\",\"authorization\":4777538941006657}"
    },
    "8d57dec5-b52d-470a-ae44-e0fe58352698": {
        "type": "benign",
        "resp": "{\"approved\":\"true\",\"authorization\":300163662421093}"
    },
    "4a302129-1478-4ddf-a93a-53da0cf06fa9": {
        "type": "benign",
        "resp": "{\"approved\":\"true\",\"authorization\":6548358574841993}"
    },
    "dcb4a98e-d87f-4822-b396-18580d095128": {
        "type": "benign",
        "resp": "{\"approved\":\"true\",\"authorization\":7368074586275723}"
    },
    "89195753-2a85-427d-af01-3c7b22ec3fbf": {
        "type": "benign",
        "resp": "{\"approved\":\"true\",\"authorization\":3574663270807419}"
    },
    "1212cfba-a9f8-4f73-8126-da25021db842": {
        "type": "benign",
        "resp": "{\"approved\":\"true\",\"authorization\":4531639766584541}"
    },
    "779be143-8077-4521-961e-0fbedbb4f4fe": {
        "type": "benign",
        "resp": "{\"approved\":\"true\",\"authorization\":6430083736933149}"
    },
    "4cdd0bf5-162f-4487-9651-cdb898ef7416": {
        "type": "benign",
        "resp": "{\"approved\":\"true\",\"authorization\":7130406574035049}"
    },
    "a85a2061-0862-4f13-aeee-f20ed4617ac6": {
        "type": "benign",
        "resp": "{\"approved\":\"true\",\"authorization\":1988073388898237}"
    },
    "7c256c99-d63c-4c08-ac49-83139fc274ee": {
        "type": "benign",
        "resp": "{\"approved\":\"true\",\"authorization\":6095714865182087}"
    },
    "8d03016e-d965-4066-9b9b-4ea1ee820327": {
        "type": "benign",
        "resp": "{\"approved\":\"true\",\"authorization\":1196375585044183}"
    }
}